LICENSE
MANIFEST.in
README.md
pyproject.toml
setup.py
acv_app/__init__.py
acv_app/app.py
acv_app/plots.py
acv_app/sdp_app.py
acv_app/sv_app.py
acv_app/colors/__init__.py
acv_app/colors/_colorconv.py
acv_app/colors/_colors.py
acv_explainers/__init__.py
acv_explainers/acv_agnosticX.py
acv_explainers/acv_tree.py
acv_explainers/base_agnostree.py
acv_explainers/base_tree.py
acv_explainers/py_acv.py
acv_explainers/setup.py
acv_explainers/utils.py
acv_explainers/utils_exp.py
acv_explainers/utils_sdp.py
acv_explainers/cext_acv/_cext.cc
acv_explainers/cext_acv/acv_tree.h
acv_explainers/cyext_acv/cyext_acv.cpp
acv_explainers/cyext_acv/cyext_acv.pyx
acv_explainers/cyext_acv/cyext_acv_ba.pyx
acv_explainers/cyext_acv/cyext_acv_cache.cpp
acv_explainers/cyext_acv/cyext_acv_cache.pyx
acv_explainers/cyext_acv/cyext_acv_nopa.cpp
acv_explainers/cyext_acv/cyext_acv_nopa.pyx
acv_explainers/cyext_acv/cyext_save.pyx
acvt45.egg-info/PKG-INFO
acvt45.egg-info/SOURCES.txt
acvt45.egg-info/dependency_links.txt
acvt45.egg-info/not-zip-safe
acvt45.egg-info/requires.txt
acvt45.egg-info/top_level.txt
experiments/__init__.py
experiments/exp_linear.py
experiments/exp_linear_gmm.py
experiments/exp_linear_gmm_ohe.py
experiments/exp_syn.py
experiments/shap_linear.py
experiments/utils.py