Metadata-Version: 2.1
Name: acvt45
Version: 1.1.1
Summary: ACV is a library that provides robust and accurate explanations for machine learning models
Home-page: https://github.com/salimamoukou/acv00
Author: Salim I. Amoukou
Author-email: salim.ibrahim-amoukou@universite-paris-saclay.fr
License: MIT
Platform: UNKNOWN
Provides-Extra: test
License-File: LICENSE
